engineio/__init__.py
engineio/asyncio_client.py
engineio/asyncio_server.py
engineio/asyncio_socket.py
engineio/client.py
engineio/exceptions.py
engineio/middleware.py
engineio/packet.py
engineio/payload.py
engineio/server.py
engineio/socket.py
engineio/async_drivers/__init__.py
engineio/async_drivers/aiohttp.py
engineio/async_drivers/asgi.py
engineio/async_drivers/eventlet.py
engineio/async_drivers/gevent.py
engineio/async_drivers/gevent_uwsgi.py
engineio/async_drivers/sanic.py
engineio/async_drivers/threading.py
engineio/async_drivers/tornado.py
tests/__init__.py
tests/asyncio/__init__.py
tests/asyncio/test_async_aiohttp.py
tests/asyncio/test_async_asgi.py
tests/asyncio/test_async_tornado.py
tests/asyncio/test_asyncio_client.py
tests/asyncio/test_asyncio_server.py
tests/asyncio/test_asyncio_socket.py
tests/common/__init__.py
tests/common/test_async_eventlet.py
tests/common/test_client.py
tests/common/test_middleware.py
tests/common/test_packet.py
tests/common/test_payload.py
tests/common/test_server.py
tests/common/test_socket.py
galileo_engineio-3.5.1.dist-info/LICENSE
galileo_engineio-3.5.1.dist-info/METADATA
galileo_engineio-3.5.1.dist-info/WHEEL
galileo_engineio-3.5.1.dist-info/top_level.txt
galileo_engineio-3.5.1.dist-info/RECORD
